cftools.py
cftoolstext-1.0.0.dist-info/METADATA
cftoolstext-1.0.0.dist-info/WHEEL
cftoolstext-1.0.0.dist-info/top_level.txt
cftoolstext-1.0.0.dist-info/RECORD
