Metadata-Version: 2.4
Name: cftoolstext
Version: 1.0.0
Summary: Library for multi-level encoding and file operations
Author: Feller
Author-email: false.fas527@gmail.com
Classifier: Programming Language :: Python :: 3
Classifier: License :: OSI Approved :: MIT License
Classifier: Operating System :: OS Independent
Requires-Python: >=3.6
Dynamic: author
Dynamic: author-email
Dynamic: classifier
Dynamic: description
Dynamic: description-content-type
Dynamic: requires-python
Dynamic: summary
